grasping_learning_data_generator/__init__.py
grasping_learning_data_generator/orientation.py
grasping_learning_data_generator/position.py
grasping_learning_data_generator/transformations.py
grasping_learning_data_generator-2.1.2.dist-info/LICENSE
grasping_learning_data_generator-2.1.2.dist-info/METADATA
grasping_learning_data_generator-2.1.2.dist-info/WHEEL
grasping_learning_data_generator-2.1.2.dist-info/top_level.txt
grasping_learning_data_generator-2.1.2.dist-info/RECORD
