Metadata-Version: 2.1
Name: grasping-learning-data-generator
Version: 2.1.2
Summary: Generates learning data for grasping data from NEEMs
Home-page: https://github.com/code-iai/grasping-learning-data-generator
Author: Sebastian Koralewski
Author-email: seba@cs.uni-bremen.de
License: UNKNOWN
Platform: UNKNOWN
Classifier: Programming Language :: Python :: 2
Classifier: License :: OSI Approved :: MIT License
Classifier: Operating System :: OS Independent
Requires-Dist: high-level-markov-logic-network (==1.0.1)
Requires-Dist: pandas (==0.22.0)
Requires-Dist: cram2wordnet (==1.0.1)
